aiogram_listview/__init__.py
aiogram_listview/listview.py
aiogram_listview/listview_aiogram.py
aiogram_listview/listview_controller.py
aiogram_listview/listview_storage.py
aiogram_listview-0.0.1.dist-info/METADATA
aiogram_listview-0.0.1.dist-info/WHEEL
aiogram_listview-0.0.1.dist-info/top_level.txt
aiogram_listview-0.0.1.dist-info/RECORD
